telegram_python/__init__.py
telegram_python/telegram_send.py
nitra_telegram_python-0.6.0.dist-info/METADATA
nitra_telegram_python-0.6.0.dist-info/WHEEL
nitra_telegram_python-0.6.0.dist-info/RECORD
